muldataframe/MulDataFrame.py
muldataframe/MulSeries.py
muldataframe/ValFrameBase.py
muldataframe/__init__.py
muldataframe/cmm.py
muldataframe/util.py
muldataframe-0.1.2.dist-info/METADATA
muldataframe-0.1.2.dist-info/WHEEL
muldataframe-0.1.2.dist-info/licenses/LICENSE
muldataframe-0.1.2.dist-info/RECORD
