Metadata-Version: 2.4
Name: muldataframe
Version: 0.1.2
Summary: Towards a more intuitive multi-index DataFrame
Project-URL: Homepage, https://github.com/frlender/muldataframe
Project-URL: Issues, https://github.com/frlender/muldataframe/issues
Author-email: Qiaonan Duan <geonann@gmail.com>
License-File: LICENSE
Classifier: License :: OSI Approved :: GNU General Public License v3 (GPLv3)
Classifier: Operating System :: OS Independent
Classifier: Programming Language :: Python :: 3
Requires-Python: >=3.11
Requires-Dist: numpy~=1.26.3
Requires-Dist: pandas~=2.2.0
Requires-Dist: tabulate~=0.9.0
